{
  "todos": [
    {
      "id": 1,
      "title": "sdsd",
      "completed": false
    },
    {
      "id": 3,
      "title": "fugiat veniam minus",
      "completed": false
    },
    {
      "title": "kkk",
      "completed": false,
      "id": 8
    },
    {
      "title": "dsds",
      "completed": false,
      "id": 10
    },
    {
      "title": "nn",
      "completed": false,
      "id": 11
    },
    {
      "title": "hhhh",
      "completed": true,
      "id": 12
    },
    {
      "title": "nhnh",
      "completed": true,
      "id": 13
    },
    {
      "title": "nnnn",
      "completed": true,
      "id": 15
    }
  ]
}